empdist/__init__.py
empdist/constants.py
empdist/empirical_distributions.py
empdist/empirical_distributions_rv_histogram_wrapper.py
empdist/empirical_pval.py
empdist/external_operators.py
empdist/helper_funcs.py
empdist/utilities.py
empdist-0.2.0.dist-info/LICENSE
empdist-0.2.0.dist-info/METADATA
empdist-0.2.0.dist-info/WHEEL
empdist-0.2.0.dist-info/top_level.txt
empdist-0.2.0.dist-info/RECORD
