Metadata-Version: 2.1
Name: empdist
Version: 0.2.0
Summary: Python class and helper functions for modeling and manipulating empirical distributions 
Home-page: https://github.com/phageghost/empirical-distribution
Author: Dylan Skola
Author-email: empdist@phageghost.net
License: MIT
Platform: UNKNOWN
Classifier: Programming Language :: Python :: 3
Classifier: License :: OSI Approved :: MIT License
Classifier: Operating System :: OS Independent
Requires-Dist: numpy
Requires-Dist: scipy (>=0.19)
